AUTHORS.rst
CONTRIBUTING.rst
HISTORY.rst
LICENSE
MANIFEST.in
README.md
setup.cfg
setup.py
cookie_monster/__init__.py
cookie_monster/apps.py
cookie_monster/settings.py
cookie_monster/urls.py
cookie_monster/utils.py
cookie_monster/static/cookie_monster/css/minimal.css
cookie_monster/static/cookie_monster/js/cookie-monster.esm.js
cookie_monster/static/cookie_monster/js/cookie-monster.esm.js.map
cookie_monster/static/cookie_monster/js/cookie-monster.umd.js
cookie_monster/static/cookie_monster/js/cookie-monster.umd.js.map
cookie_monster/templates/cookie_monster/base.html
cookie_monster/templatetags/__init__.py
cookie_monster/templatetags/cookie_monster.py
django_cookie_monster.egg-info/PKG-INFO
django_cookie_monster.egg-info/SOURCES.txt
django_cookie_monster.egg-info/dependency_links.txt
django_cookie_monster.egg-info/not-zip-safe
django_cookie_monster.egg-info/top_level.txt
tests/test_models.py