Metadata-Version: 2.1
Name: django-cookie-monster
Version: 0.1.8.2
Summary: Your project description goes here
Home-page: https://github.com/victoriameyer/django-cookie-monster
Author: dreipol GmbH
Author-email: dev@dreipol.ch
License: BSD
Keywords: django-cookie-monster
Classifier: Development Status :: 3 - Alpha
Classifier: Framework :: Django :: 1.11
Classifier: Framework :: Django :: 2.0
Classifier: Intended Audience :: Developers
Classifier: License :: OSI Approved :: BSD License
Classifier: Natural Language :: English
Classifier: Programming Language :: Python :: 2
Classifier: Programming Language :: Python :: 2.7
Classifier: Programming Language :: Python :: 3
Classifier: Programming Language :: Python :: 3.4
Classifier: Programming Language :: Python :: 3.5
Classifier: Programming Language :: Python :: 3.6
License-File: LICENSE
License-File: AUTHORS.rst
